nti.app.pyramid_zope-0.0.3-py3.8-nspkg.pth
nti/app/pyramid_zope/__init__.py
nti/app/pyramid_zope/configure.zcml
nti/app/pyramid_zope/pyramid.zcml
nti/app/pyramid_zope/request.py
nti/app/pyramid_zope/security.py
nti/app/pyramid_zope/traversal.py
nti/app/pyramid_zope/z3c_zpt.py
nti/app/pyramid_zope/i18n/__init__.py
nti/app/pyramid_zope/i18n/adapters.py
nti/app/pyramid_zope/i18n/configure.zcml
nti/app/pyramid_zope/i18n/interfaces.py
nti/app/pyramid_zope/i18n/pyramid.zcml
nti/app/pyramid_zope/i18n/subscribers.py
nti/app/pyramid_zope/i18n/tests/__init__.py
nti/app/pyramid_zope/i18n/tests/test_adapters.py
nti/app/pyramid_zope/i18n/tests/test_subscribers.py
nti/app/pyramid_zope/locales/nti.app.pyramid_zope.pot
nti/app/pyramid_zope/tests/__init__.py
nti/app/pyramid_zope/tests/test_request.py
nti/app/pyramid_zope/tests/test_security.py
nti/app/pyramid_zope/tests/test_traversal.py
nti.app.pyramid_zope-0.0.3.dist-info/AUTHORS
nti.app.pyramid_zope-0.0.3.dist-info/LICENSE
nti.app.pyramid_zope-0.0.3.dist-info/METADATA
nti.app.pyramid_zope-0.0.3.dist-info/WHEEL
nti.app.pyramid_zope-0.0.3.dist-info/entry_points.txt
nti.app.pyramid_zope-0.0.3.dist-info/namespace_packages.txt
nti.app.pyramid_zope-0.0.3.dist-info/top_level.txt
nti.app.pyramid_zope-0.0.3.dist-info/zip-safe
nti.app.pyramid_zope-0.0.3.dist-info/RECORD
