Metadata-Version: 2.1
Name: nti.app.pyramid-zope
Version: 0.0.3
Summary: Support for a more Zope-like pyramid.
Home-page: https://github.com/NextThought/nti.app.pyramid_zope
Author: Jason Madden
Author-email: jason@nextthought.com
License: Apache
Keywords: pyramid zope
Platform: UNKNOWN
Classifier: Framework :: Pyramid
Classifier: Framework :: Zope :: 3
Classifier: Intended Audience :: Developers
Classifier: Natural Language :: English
Classifier: Operating System :: OS Independent
Classifier: Development Status :: 3 - Alpha
Classifier: Programming Language :: Python :: 2
Classifier: Programming Language :: Python :: 2.7
Classifier: Programming Language :: Python :: 3
Classifier: Programming Language :: Python :: 3.6
Classifier: Programming Language :: Python :: 3.7
Classifier: Programming Language :: Python :: 3.8
Classifier: Programming Language :: Python :: 3.9
Classifier: Programming Language :: Python :: Implementation :: CPython
Classifier: Programming Language :: Python :: Implementation :: PyPy
Requires-Python: >=2.7,!=3.0.*,!=3.1.*,!=3.2.*,!=3.3.*,!=3.4.*,!=3.5
License-File: LICENSE
License-File: AUTHORS
Requires-Dist: Chameleon
Requires-Dist: PyYAML
Requires-Dist: nti.property
Requires-Dist: nti.traversal
Requires-Dist: pyramid (<2.0)
Requires-Dist: pyramid-chameleon
Requires-Dist: setuptools
Requires-Dist: simplejson
Requires-Dist: six
Requires-Dist: z3c.pt
Requires-Dist: z3c.ptcompat
Requires-Dist: z3c.template
Requires-Dist: zope.authentication
Requires-Dist: zope.browserpage
Requires-Dist: zope.cachedescriptors
Requires-Dist: zope.component
Requires-Dist: zope.configuration
Requires-Dist: zope.dottedname
Requires-Dist: zope.i18n
Requires-Dist: zope.interface
Requires-Dist: zope.pagetemplate
Requires-Dist: zope.principalregistry
Requires-Dist: zope.proxy
Requires-Dist: zope.publisher
Requires-Dist: zope.security
Requires-Dist: zope.traversing
Requires-Dist: zope.viewlet
Provides-Extra: docs
Requires-Dist: Sphinx ; extra == 'docs'
Requires-Dist: repoze.sphinx.autointerface ; extra == 'docs'
Requires-Dist: sphinx-rtd-theme ; extra == 'docs'
Requires-Dist: coverage ; extra == 'docs'
Requires-Dist: fudge ; extra == 'docs'
Requires-Dist: nti.testing ; extra == 'docs'
Requires-Dist: zope.testrunner ; extra == 'docs'
Provides-Extra: test
Requires-Dist: coverage ; extra == 'test'
Requires-Dist: fudge ; extra == 'test'
Requires-Dist: nti.testing ; extra == 'test'
Requires-Dist: zope.testrunner ; extra == 'test'
